Lab3/mux.v
// output = A (when control == 0) or B (when control == 1)
module mux2(out, A, B, control);
    output out;
    input  A, B;
    input  control;
    wire   wA, wB, not_control;
         
    not n1(not_control, control);
    and a1(wA, A, not_control);
    and a2(wB, B, control);
    or  o1(out, wA, wB);
endmodule // mux2

// output = A (when control == 00) or B (when control == 01) or
//          C (when control == 10) or D (when control == 11)
module mux4(out, A, B, C, D, control);
    output      out;
    input       A, B, C, D;
    input [1:0] control;
    
    wire c0,c1;
    mux2 m0(c0,A,B,control[0]);
    mux2 m1(c1,C,D,control[0]);
    mux2 m2(out,c0,c1,control[1]);
    
    

endmodule // mux4

Lab3/logicunit.v
// 00 - AND, 01 - OR, 10 - NOR, 11 - XOR
module logicunit(out, A, B, control);
    output      out;
    input       A, B;
    input [1:0] control;
    
    wire na,nb,nc0,nc1,nanbc1nc0,nabnc1c0,nabc1c0,anbnc1c0,anbc0c1,abnc0nc1,abnc1c0;
    not n1(na,A);
    not n2(nb,B);
    not n3(nc0,control[0]);    
    not n4(nc1,control[1]);
    
    and a1(nanbc1nc0,na,nb,control[1],nc0);
    and a2(nabnc1c0,na,B,control[0],nc1);
    and a3(nabc1c0,na,B,control[0],control[1]);
    and a4(anbnc1c0,A,nb,control[0],nc1);
    and a5(anbc0c1,A,nb,control[0],control[1]);
    and a6(abnc0nc1,A,B,nc1,nc0);
    and a7(abnc1c0,A,B,control[0],nc1);         
    
    or(out,nabc1c0,nabnc1c0,nanbc1nc0,anbc0c1,anbnc1c0,abnc0nc1,abnc1c0);   
    
    
endmodule // logicunit

Lab3/alu1.v
module full_adder(sum, cout, a, b, cin);
    output sum, cout;
    input  a, b, cin;
    wire   partial_s, partial_c1, partial_c2;

    xor x0(partial_s, a, b);
    xor x1(sum, partial_s, cin);
    and a0(partial_c1, a, b);
    and a1(partial_c2, partial_s, cin);
    or  o1(cout, partial_c1, partial_c2);
endmodule // full_adder

`define ALU_ADD    3'h2
`define ALU_SUB    3'h3
`define ALU_AND    3'h4
`define ALU_OR     3'h5
`define ALU_NOR    3'h6
`define ALU_XOR    3'h7

// 01x - arithmetic, 1xx - logic
module alu1(out, carryout, A, B, carryin, control);
    output      out, carryout;
    input       A, B, carryin;
    input [2:0] control;
	
	wire x,y,sub,c0,c1,c2,nc0,nc1,nc2,ar,log;
	not nn(nc2,control[2]);
	xor x0(y,B,control[0]);
	full_adder f0(ar,carryout,A,y,carryin);
	logicunit log0(log,A,B,control[1:0]);
	
	mux2 mselect(out,ar,log,control[2]);
    // add code here!!!
   
endmodule // alu1

Lab3/alu1_tb.v
module alu1_test;
    // exhaustively test your 1-bit ALU by adapting mux4_tb.v
    reg A,B,carryin;
    reg [2:0] control;
    
    wire out,carryout;
    
    alu1 test(out,carryout,A,B,carryin,control);
    	initial begin
    $dumpfile("alu1.vcd");                  // name of dump file to create
       $dumpvars(0,alu1_test);  
    	
        A = 0; B = 0;carryin = 0;   control = 010; # 10; 
        A = 0; B = 1;carryin = 0;   control = 010; # 10; 
        A = 1; B = 0;carryin = 0;   control = 010; # 10; 
        A = 1; B = 1;carryin = 0;   control = 010; # 10; 
        A = 0; B = 0;carryin = 0;   control = 011; # 10; 
        A = 0; B = 1;carryin = 0;   control = 011; # 10; 
        A = 1; B = 0;carryin = 0;   control = 011; # 10; 
        A = 1; B = 1;carryin = 0;   control = 011; # 10;
        A = 0; B = 0;carryin = 0;   control = 100; # 10; 
        A = 0; B = 1;carryin = 0;   control = 100; # 10; 
        A = 1; B = 0;carryin = 0;   control = 100; # 10; 
        A = 1; B = 1;carryin = 0;   control = 100; # 10;
        A = 0; B = 0;carryin = 0;   control = 101; # 10; 
        A = 0; B = 1;carryin = 0;   control = 101; # 10; 
        A = 1; B = 0;carryin = 0;   control = 101; # 10; 
        A = 1; B = 1;carryin = 0;   control = 101; # 10;
        A = 0; B = 0;carryin = 0;   control = 110; # 10; 
        A = 0; B = 1;carryin = 0;   control = 110; # 10; 
        A = 1; B = 0;carryin = 0;   control = 110; # 10; 
        A = 1; B = 1;carryin = 0;   control = 110; # 10;
        A = 0; B = 0;carryin = 0;   control = 111; # 10; 
        A = 0; B = 1;carryin = 0;   control = 111; # 10; 
        A = 1; B = 0;carryin = 0;   control = 111; # 10; 
        A = 1; B = 1;carryin = 0;   control = 111; # 10;                                
        $finish;                              // end the simulation
    end                      
    
    initial
        $monitor("At time %2t, A = %d B = %d control = %d out = %d cout = %d",
                 $time, A, B, control , out, carryout);
endmodule

Lab3/alu1.vcd
$date
	Fri Sep 15 20:22:12 2017
$end
$version
	Icarus Verilog
$end
$timescale
	1s
$end
$scope module alu1_test $end
$var wire 1 ! carryout $end
$var wire 1 " out $end
$var reg 1 # A $end
$var reg 1 $ B $end
$var reg 1 % carryin $end
$var reg 3 & control [2:0] $end
$scope module test $end
$var wire 1 ' A $end
$var wire 1 ( B $end
$var wire 1 ) ar $end
$var wire 1 * carryin $end
$var wire 1 ! carryout $end
$var wire 3 + control [2:0] $end
$var wire 1 , log $end
$var wire 1 - nc2 $end
$var wire 1 " out $end
$var wire 1 . y $end
$scope module f0 $end
$var wire 1 ' a $end
$var wire 1 . b $end
$var wire 1 * cin $end
$var wire 1 ! cout $end
$var wire 1 / partial_c1 $end
$var wire 1 0 partial_c2 $end
$var wire 1 1 partial_s $end
$var wire 1 ) sum $end
$upscope $end
$scope module log0 $end
$var wire 1 ' A $end
$var wire 1 ( B $end
$var wire 1 2 abnc0nc1 $end
$var wire 1 3 abnc1c0 $end
$var wire 1 4 anbc0c1 $end
$var wire 1 5 anbnc1c0 $end
$var wire 2 6 control [1:0] $end
$var wire 1 7 na $end
$var wire 1 8 nabc1c0 $end
$var wire 1 9 nabnc1c0 $end
$var wire 1 : nanbc1nc0 $end
$var wire 1 ; nb $end
$var wire 1 < nc0 $end
$var wire 1 = nc1 $end
$var wire 1 , out $end
$upscope $end
$scope module mselect $end
$var wire 1 ) A $end
$var wire 1 , B $end
$var wire 1 > control $end
$var wire 1 ? not_control $end
$var wire 1 " out $end
$var wire 1 @ wA $end
$var wire 1 A wB $end
$upscope $end
$upscope $end
$upscope $end
$enddefinitions $end
#0
$dumpvars
0A
0@
1?
0>
0=
1<
1;
1:
09
08
17
b10 6
05
04
03
02
01
00
0/
0.
1-
1,
b10 +
0*
0)
0(
0'
b10 &
0%
0$
0#
0"
0!
$end
#10
1"
1@
0,
1)
11
0:
1.
0;
1$
1(
#20
1"
1@
1)
0!
0.
1;
11
0/
07
0$
0(
1#
1'
#30
0"
0@
0)
1!
01
1/
1.
0;
1$
1(
#40
1"
0,
0<
1@
1)
0!
0:
b11 6
1.
1;
11
0/
17
b11 &
b11 +
0$
0(
0#
0'
#50
0"
0@
0)
1,
01
0.
0;
18
1$
1(
#60
0"
1!
1,
0@
1/
14
0)
1.
1;
08
01
07
0$
0(
1#
1'
#70
1"
1@
0,
1)
0!
11
0/
04
0.
0;
1$
1(
#80
0"
1<
1=
0@
0-
0?
0)
b0 6
1>
0.
1;
01
17
b100 &
b100 +
0$
0(
0#
0'
#90
1)
11
1.
0;
1$
1(
#100
1)
0!
0.
1;
11
0/
07
0$
0(
1#
1'
#110
1"
1A
0)
1!
1,
01
1/
1.
0;
12
1$
1(
#120
0"
0A
0<
0,
1)
0!
b1 6
1.
1;
11
0/
17
02
b101 &
b101 +
0$
0(
0#
0'
#130
1"
1A
0)
1,
01
0.
0;
19
1$
1(
#140
1"
1A
1!
1,
1/
15
0)
1.
1;
09
01
07
0$
0(
1#
1'
#150
1)
0!
11
0/
05
0.
0;
13
1$
1(
#160
1"
1:
1A
1<
0=
1,
0)
b10 6
0.
1;
01
17
03
b110 &
b110 +
0$
0(
0#
0'
#170
0"
0A
0,
1)
11
0:
1.
0;
1$
1(
#180
1)
0!
0.
1;
11
0/
07
0$
0(
1#
1'
#190
0)
1!
01
1/
1.
0;
1$
1(
#200
0"
0A
0,
0<
1)
0!
0:
b11 6
1.
1;
11
0/
17
b111 &
b111 +
0$
0(
0#
0'
#210
1"
1A
0)
1,
01
0.
0;
18
1$
1(
#220
1"
1A
1!
1,
1/
14
0)
1.
1;
08
01
07
0$
0(
1#
1'
#230
0"
0A
0,
1)
0!
11
0/
04
0.
0;
1$
1(
