Lab3/logicunit.v
// 00 - AND, 01 - OR, 10 - NOR, 11 - XOR
module logicunit(out, A, B, control);
    output      out;
    input       A, B;
    input [1:0] control;
    
    wire na,nb,nc0,nc1,nanbc1nc0,nabnc1c0,nabc1c0,anbnc1c0,anbc0c1,abnc0nc1,abnc1c0;
    not n1(na,A);
    not n2(nb,B);
    not n3(nc0,control[0]);    
    not n4(nc1,control[1]);
    
    and a1(nanbc1nc0,na,nb,control[1],nc0);
    and a2(nabnc1c0,na,B,control[0],nc1);
    and a3(nabc1c0,na,B,control[0],control[1]);
    and a4(anbnc1c0,A,nb,control[0],nc1);
    and a5(anbc0c1,A,nb,control[0],control[1]);
    and a6(abnc0nc1,A,B,nc1,nc0);
    and a7(abnc1c0,A,B,control[0],nc1);         
    
    or(out,nabc1c0,nabnc1c0,nanbc1nc0,anbc0c1,anbnc1c0,abnc0nc1,abnc1c0);   
    
    
endmodule // logicunit

Lab3/logicunit_tb.v
module logicunit_test;
    // exhaustively test your logic unit by adapting mux4_tb.v
    reg A,B;
    reg [1:0] control;
    
    wire out;
    
    logicunit test(out,A,B,control);
      initial begin                             // initial = run at beginning of simulation
                                              // begin/end = associate block with initial
 
       $dumpfile("logicunit.vcd");                  // name of dump file to create
       $dumpvars(0,logicunit_test);                 // record all signals of module "sc_test" and sub-mo
       
        A = 0; B = 0; control = 00; # 10;             // set initial values and wait 10 time units
        A = 0; B = 1; control = 00; # 10; 
        A = 1; B = 0; control = 00; # 10; 
        A = 1; B = 1; control = 00; # 10; 
        A = 0; B = 0; control = 01; # 10; 
        A = 0; B = 1; control = 01; # 10; 
        A = 1; B = 0; control = 01; # 10; 
        A = 1; B = 1; control = 01; # 10; 
        A = 0; B = 0; control = 10; # 10; 
        A = 0; B = 1; control = 10; # 10; 
        A = 1; B = 0; control = 10; # 10; 
        A = 1; B = 1; control = 10; # 10; 
        A = 0; B = 0; control = 11; # 10; 
        A = 0; B = 1; control = 11; # 10; 
        A = 1; B = 0; control = 11; # 10; 
        A = 1; B = 1; control = 11; # 10;                                                                 
 
        $finish;                              // end the simulation
    end                      
    
    initial
        $monitor("At time %2t, A = %d B = %d control = %d out = %d",
                 $time, A, B, control , out);
    
endmodule // logicunit_test

Lab3/logicunit.vcd
$date
	Fri Sep 15 20:19:44 2017
$end
$version
	Icarus Verilog
$end
$timescale
	1s
$end
$scope module logicunit_test $end
$var wire 1 ! out $end
$var reg 1 " A $end
$var reg 1 # B $end
$var reg 2 $ control [1:0] $end
$scope module test $end
$var wire 1 % A $end
$var wire 1 & B $end
$var wire 1 ' abnc0nc1 $end
$var wire 1 ( abnc1c0 $end
$var wire 1 ) anbc0c1 $end
$var wire 1 * anbnc1c0 $end
$var wire 2 + control [1:0] $end
$var wire 1 , na $end
$var wire 1 - nabc1c0 $end
$var wire 1 . nabnc1c0 $end
$var wire 1 / nanbc1nc0 $end
$var wire 1 0 nb $end
$var wire 1 1 nc0 $end
$var wire 1 2 nc1 $end
$var wire 1 ! out $end
$upscope $end
$upscope $end
$enddefinitions $end
#0
$dumpvars
12
11
10
0/
0.
0-
1,
b0 +
0*
0)
0(
0'
0&
0%
b0 $
0#
0"
0!
$end
#10
00
1#
1&
#20
10
0,
0#
0&
1"
1%
#30
1!
00
1'
1#
1&
#40
0!
01
10
1,
0'
b1 $
b1 +
0#
0&
0"
0%
#50
1!
00
1.
1#
1&
#60
1!
1*
10
0.
0,
0#
0&
1"
1%
#70
0*
00
1(
1#
1&
#80
1/
1!
11
02
10
1,
0(
b10 $
b10 +
0#
0&
0"
0%
#90
0!
0/
00
1#
1&
#100
10
0,
0#
0&
1"
1%
#110
00
1#
1&
#120
0!
01
0/
10
1,
b11 $
b11 +
0#
0&
0"
0%
#130
1!
00
1-
1#
1&
#140
1!
1)
10
0-
0,
0#
0&
1"
1%
#150
0!
0)
00
1#
1&
